Workbook

Sheet Sheet2
A3: Row Labels
A4: CR
A5: (blank)
A6: (blank)
A7: (blank)
A8: (blank)
A9: MASSIMO DUTTI ESCAZU
A10: STRADIVARIUS DEL ESTE
A11: GT
A12: (blank)
A13: MASSIMO DUTTI OAKLAND
A14: (blank)
... A47: Grand Total

Sheet Sheet4
A1: SELECCIONA EL PAÍS. | B1: SV
B3: Column Labels
B4: No | E4: Total Sum of Id | F4: Total Count of Comentarios sobre la bienvenida. | G4: Total Count of ¿Se presentó a su formador?
A5: Row Labels | B5: Sum of Id | C5: Count of Comentarios sobre la bienvenida. | D5: Count of ¿Se presentó a su formador?
A6: BERSHKA LA GRAN VIA | B6: 3 | C6: 1 | D6: 1 | E6: 3 | F6: 1 | G6: 1
A7: Osiris Gabriel Moran Cuellar | B7: 3 | C7: 1 | D7: 1 | E7: 3 | F7: 1 | G7: 1
A8: ZARA LA GRAN VIA | B8: 1 | C8: 1 | D8: 1 | E8: 1 | F8: 1 | G8: 1
A9: Osiris Gabriel Moran Cuellar | B9: 1 | C9: 1 | D9: 1 | E9: 1 | F9: 1 | G9: 1
A10: Grand Total | B10: 4 | C10: 2 | D10: 2 | E10: 4 | F10: 2 | G10: 2

Sheet Sheet1
A1: Id | B1: Column1 | C1: Hora de inicio | D1: Hora de finalización | E1: Correo electrónico | F1: Nombre | G1: NOMBRE COMPLETO (ENCAGADO DE RH O RECLUTAMIENTO) | H1: ID DE COLABORADOR DEL EMPLEADO A ENTREVISTAR | I1: SELECCIONA EL PAÍS. | J1: TIENDAS EN EL SALVADOR | K1: BERSHKA GALERIAS | L1: LA GRAN VIA | M1: OFICINAS CORPORATIVAS | N1: FLYING TIGER | O1: OYSHO LA GRAN VIA | P1: PACKING SV | Q1: PULL AND BEAR GALERIAS | R1: PULL AND BEAR LA GRAN VIA | S1: STRAVARIUS GALERIAS | T1: STRADIVARIUS LA GRAN VIA | U1: ZARA LA GRAN VIA | V1: SELECCIONA TU TIENDA EN GUATEMALA | W1: BSK MIRAFLORES | X1: BSK OAKLAND | Y1: BSK PRADERA CONCEPCCIÓN | Z1: OFICINAS CORPORATIVAS1 | AA1: MASSIMO DUTTI | AB1: OYSHO OAKLAND | AC1: PACKING GT | AD1: PULL AND BEAR MIRAFLORES | AE1: PULL AND BEAR OAKLAND | AF1: PULL AND BEAR PRADERA CONCEPCIÓN | AG1: STRADIVARIUS MIRAFLORES | AH1: STRADIVARIUS OAKLAND | AI1: STRADIVARIUS PRADERA CONCEPCIÓN | AJ1: ZARA HOME GT | AK1: ZARA MIRAFLORES | AL1: ZARA OAKLAND | AM1: ZARA PRADERA CONCEPCIÓN | AN1: SELECCIONA LA TIENDA EN HONDURAS | AO1: BSK SAN PEDRO SULA | AP1: BSK TEGUCIGALPA | AQ1: MASSIMO DUTTI TEGUCIGALPA | AR1: OYSHO TEGUCIGALPA | AS1: PULL AND BEAR SAN PEDRO SULA | AT1: PULL AND BEAR TEGUCIGALPA | AU1: STRADIVARIUS SAN PEDRO SULA | AV1: STRADIVARIUS TEGUCIGALPA | AW1: ZARA CITY MALL | AX1: ZARA HOME TEGUCIGALPA | AY1: ZARA TEGUCIGALPA | AZ1: SELECCIONA TU TIENDA EN NICARAGUA | BA1: BSK SANTO DOMINGO | BB1: PULL AND BEAR SANTO DOMINGO | BC1: STRADIVARIUS SANTO DOMINGO | BD1: ZARA SANTO DOMINGO | BE1: SELECCIONA LA TIENDA DE COSTA RICA | BF1: BERSHKA MULTIPLAZA DEL ESTE | BG1: BSK MULTIPLAZA ESCAZU | BH1: ZARA HOME COSTA RICA | BI1: MASSIMO DUTTI ESCAZU | BJ1: OFICINAS CR | BK1: OYSHO ESCAZU | BL1: PULL AND BEAR DEL ESTE | BM1: PULL AND BEAR ESCAZU | BN1: STRADIVARIUS DEL ESTE | BO1: STRADIVARIUS ESCAZU | BP1: ZARA DEL ESTE | BQ1: ZARA ESCAZU | BR1: SELECCIONA EL CONTACTO | BS1: ESCRIBE EL CODIGO DE COLABORADOR | BT1: Se Sintió Bienvenido | BU1: Comentarios sobre la bienvenida. | BV1: ¿Se presentó a su formador? | BW1: Nombre del Formador | BX1: Tiene cuenta de INET y su respectiva explicación. | BY1: Que tal le pareció su induccion | BZ1: Comentarios sobre la inducción y/o adicionales | CA1: FECHA DEL SEGUNDO CONTACTO | CB1: ESCRIBE EL CÓDIGO DE COLABORADOR | CC1: NOMBRE COMPLETO | CD1: CODIGO DE COLABORADOR | CE1: ENCARGADO DE LA TIENDA | CF1: FECHA DE INGRESO | CG1: DESEMPEÑO | CH1: CUMPLE CON LAS ASIGNACIONES DE SU PUESTO | CI1: JUSTICACIÓN | CJ1: FORMACIÓN | CK1: COMENTARIOS | CL1: FECHA ESTIMADA DE TERCER CONTACTO | CM1: CÓDIGO DE COLABORADOR1 | CN1: CODIGO DE COLABORADOR1 | CO1: PUESTO | CP1: ¿Tu encargado te ha guiado adecuadamente? | CQ1: ¿Te sientes integrado/a al equipo? | CR1: ¿Recomendarías trabajar aquí? | CS1: Comentarios1 | CT1: MOTIVO DE LA BAJA | CU1: Fecha de finalización de contrato | CV1: Comentarios adicionales
A2: 1 | B2: =OfficeForms.Table[[#This Row],[SELECCIONA EL CONTACTO]] -> PRIMER CONTACTO | C2: 46108.508 | D2: 46108.509 | E2: osiris_moran@siman.com | F2: Osiris Gabriel Moran Cuellar | I2: SV | J2: ZARA LA GRAN VIA | U2: CUELLAR RIVAS, OSCAR JOEL 5207601 DEPENDIENTE | BR2: PRIMER CONTACTO | BS2: 23423 | BT2: No | BU2: 342342 | BV2: Si | BW2: 32wewre | BX2: werwe | BY2: Regular | BZ2: werwer | CA2: 46169
A3: 2 | B3: =OfficeForms.Table[[#This Row],[SELECCIONA EL CONTACTO]] -> PRIMER CONTACTO | C3: 46111.424 | D3: 46111.432 | E3: cindy_martinez@siman.com | F3: Cindy Johanna Martinez Betancourt | G3: Cindy Martinez | H3: 1234 | I3: HO | AN3: BERSHKA SAN PEDRO SULA | BR3: PRIMER CONTACTO | BS3: 1234 | BT3: Si | BU3: Todo bien | BV3: Si | BW3: Juan Perez | BX3: No aun no | BY3: Excelente | BZ3: Todo bien | CA3: 46155
A4: 3 | B4: =OfficeForms.Table[[#This Row],[SELECCIONA EL CONTACTO]] -> PRIMER CONTACTO | C4: 46111.624 | D4: 46111.625 | E4: osiris_moran@siman.com | F4: Osiris Gabriel Moran Cuellar | G4: OSIRIS MORAN | H4: 3607801 | I4: SV | J4: BERSHKA LA GRAN VIA | L4: BARAHONA CABRERA, CLARISSA SARAI DEPENDIENTE | BR4: PRIMER CONTACTO | BS4: 123 | BT4: No | BU4: no fue bienvenido solo lo mandaron a trabajar | BV4: Si | BW4: nombre de prueba | BX4: no | BY4: Muy Mala | BZ4: se adapto muy bien | CA4: 46172
A5: 4 | B5: =OfficeForms.Table[[#This Row],[SELECCIONA EL CONTACTO]] -> SEGUNDO CONTACTO | C5: 46118.42 | D5: 46118.421 | E5: osiris_moran@siman.com | F5: Osiris Gabriel Moran Cuellar | G5: osiris moran | H5: 3607801 | I5: HO | AN5: BERSHKA TEGUCIGALPA | AP5: VELASQUEZ ORELLANA, ERNESTO ENRIQUE 1284904 DEPENDIENTE | BR5: SEGUNDO CONTACTO | CB5: 2323423 | CC5: ARSDSFG | CD5: 23123 | CE5: DFSDFSD | CF5: 46113 | CG5: 7 | CH5: 7 | CI5: ASDSDA | CJ5: 7 | CK5: DFSDFS | CL5: 46181
A6: 5 | B6: =OfficeForms.Table[[#This Row],[SELECCIONA EL CONTACTO]] -> PRIMER CONTACTO | C6: 46118.455 | D6: 46118.463 | E6: lizeth_perez@siman.com | F6: Stephanie Lizeth Ballina Perez | G6: Stephanie Ballina Perez | H6: 2142703 | I6: CR | BE6: MASSIMO DUTTI ESCAZU | BI6: CORRALES RIVERA, KRISTEL DARIANA 2371703 DEPENDIENTE | BR6: PRIMER CONTACTO | BS6: 2371703 | BT6: Si | BU6: Fue muy bonita, muy cálida, tuvieron mucho entendimiento ya que era nueva. | BV6: Si | BW6: Sayling Delgado | BX6: si | BY6: Excelente
A7: 6 | B7: =OfficeForms.Table[[#This Row],[SELECCIONA EL CONTACTO]] -> PRIMER CONTACTO | C7: 46118.463 | D7: 46118.465 | E7: lizeth_perez@siman.com | F7: Stephanie Lizeth Ballina Perez | G7: Stephanie Ballina Perez | H7: 2142703 | I7: CR | BE7: MASSIMO DUTTI ESCAZU | BI7: AGUILAR GONZALEZ, KIARA SOFIA 2499503 DEPENDIENTE | BR7: PRIMER CONTACTO | BS7: 2371703 | BT7: Si | BU7: Fue una bienvenida muy tranquila ya que me explicaron todo sobre la tienda y son muy atentas todas. | BV7: Si | BW7: Nicole Navarrete | BX7: si | BY7: Excelente
B8: =OfficeForms.Table[[#This Row],[SELECCIONA EL CONTACTO]] -> PRIMER CONTACTO | BR8: PRIMER CONTACTO
A9: 7 | B9: =OfficeForms.Table[[#This Row],[SELECCIONA EL CONTACTO]] -> PRIMER CONTACTO | C9: 46118.693 | D9: 46118.694 | E9: osiris_moran@siman.com | F9: Osiris Gabriel Moran Cuellar | G9: OSIRIS MORAN| | H9: 3607801 | I9: CR | BE9: STRADIVARIUS DEL ESTE | BN9: CALDERON SANCHO, SCARLETTE PAOLA 2480703 DEPENDIENTE | BR9: PRIMER CONTACTO | BS9: 4444444 | BT9: Si | BU9: 4444 | BV9: No | BW9: SDFSDF | BX9: qeqweq | BY9: Excelente | BZ9: muy buena | CA9: 46181
A10: 8 | B10: =OfficeForms.Table[[#This Row],[SELECCIONA EL CONTACTO]] -> TERCER CONTACTO | C10: 46118.767 | D10: 46118.767 | E10: osiris_moran@siman.com | F10: Osiris Gabriel Moran Cuellar | G10: osiris moran1 | H10: 123456 | I10: GT | V10: MASSIMO DUTTI OAKLAND | AA10: MENDEZ GARCIA, DAVID ALEJANDRO 2453406 SEGUNDO ENCARGADO | BR10: TERCER CONTACTO | CM10: ewerwe | CN10: wet24 | CO10: etsda | CP10: NO | CQ10: NO | CR10: 1 | CS10: 12
B11: =OfficeForms.Table[[#This Row],[SELECCIONA EL CONTACTO]] -> 0
A12: 9 | B12: =OfficeForms.Table[[#This Row],[SELECCIONA EL CONTACTO]] -> SEGUNDO CONTACTO | C12: 46119.597 | D12: 46119.598 | E12: osiris_moran@siman.com | F12: Osiris Gabriel Moran Cuellar | G12: OSIRIS MORAN | H12: 3229106 | I12: GT | V12: BERSHKA OAKLAND | X12: NAJERA PAREDES, DERICK JOSE ANDRES 3229106 AUXILIAR DE ALMACEN | BR12: SEGUNDO CONTACTO | CB12: 3229106 | CC12: NOMBRE DE PRUEBA | CE12: ENCARGADO DE PREUBA | CF12: 46119 | CG12: 8 | CH12: 8 | CI12: HOLA | CJ12: 8 | CK12: SI SI | CL12: 46189
B13: =OfficeForms.Table[[#This Row],[SELECCIONA EL CONTACTO]] -> 0
A14: 10 | B14: =OfficeForms.Table[[#This Row],[SELECCIONA EL CONTACTO]] -> SEGUNDO CONTACTO | C14: 46119.929 | D14: 46119.93 | E14: osiris_moran@siman.com | F14: Osiris Gabriel Moran Cuellar | G14: osiris | H14: 2458003 | I14: CR | BE14: BERSHKA ESCAZU | BG14: CASTRO AGUERO, ALEXA JIREH 2458003 DEPENDIENTE | BR14: SEGUNDO CONTACTO | CB14: 2458003 | CC14: jiret | CD14: 2458003 | CE14: no se | CF14: 46113 | CG14: 9 | CH14: 7 | CI14: hola | CJ14: 8 | CK14: casito | CL14: 46181

Sheet Hoja1
A1: PAIS | B1: EMPRESA | C1: NEGOCIO | D1: CENTRO COSTO | E1: UNIDAD | F1: LUGAR TRABAJO | G1: COLABORADOR | H1: ID COLABORADOR | I1: PUESTO | J1: INGRESO | K1: RESPONSABLE UNIDAD | L1: PRIMER C
A2: Costa Rica | B2: JOVENMODA | C2: TIENDAS DE MODA | D2: GENERICO DE VENTAS PARA TIENDAS | E2: TIENDA BERSHKA DEL ESTE | F2: BERSHKA MULTIPLAZA DEL ESTE | G2: ABBOTT MUÑOZ, SOPHIA | H2: 2458303 | I2: DEPENDIENTE | J2: 46023 | K2: DOMINGUEZ SALAZAR, BLAS ARTURO | L2: =VLOOKUP(H2,Sheet1!H:H,2,0) -> #N/A
A3: Costa Rica | B3: JOVENMODA | C3: TIENDAS DE MODA | D3: GENERICO DE VENTAS PARA TIENDAS | E3: TIENDA BERSHKA DEL ESTE | F3: BERSHKA MULTIPLAZA DEL ESTE | G3: AJÚ CASTRO, MEYBEL ALEXA | H3: 2463403 | I3: DEPENDIENTE | J3: 46023 | K3: DOMINGUEZ SALAZAR, BLAS ARTURO | L3: =VLOOKUP(H3,Sheet1!H:H,1,0) -> #N/A
A4: Costa Rica | B4: JOVENMODA | C4: TIENDAS DE MODA | D4: GENERICO DE VENTAS PARA TIENDAS | E4: TIENDA BERSHKA DEL ESTE | F4: BERSHKA MULTIPLAZA DEL ESTE | G4: ARCHIBOLD LOPEZ, YOSANTIA BRITANY | H4: 2370903 | I4: DEPENDIENTE | J4: 45658 | K4: DOMINGUEZ SALAZAR, BLAS ARTURO | L4: =VLOOKUP(H4,Sheet1!H:H,1,0) -> #N/A
A5: Costa Rica | B5: JOVENMODA | C5: TIENDAS DE MODA | D5: GENERICO DE VENTAS PARA TIENDAS | E5: TIENDA BERSHKA DEL ESTE | F5: BERSHKA MULTIPLAZA DEL ESTE | G5: BADILLA MARIN, FLOR MARIA | H5: 2364303 | I5: DEPENDIENTE | J5: 45658 | K5: DOMINGUEZ SALAZAR, BLAS ARTURO | L5: =VLOOKUP(H5,Sheet1!H:H,1,0) -> #N/A
A6: Costa Rica | B6: JOVENMODA | C6: TIENDAS DE MODA | D6: GENERICO DE VENTAS PARA TIENDAS | E6: TIENDA BERSHKA DEL ESTE | F6: BERSHKA MULTIPLAZA DEL ESTE | G6: BLANCO BERMUDEZ, JOSE JULIAN | H6: 2369203 | I6: AUXILIAR DE ALMACEN | J6: 45689 | K6: DOMINGUEZ SALAZAR, BLAS ARTURO | L6: =VLOOKUP(H6,Sheet1!H:H,1,0) -> #N/A
A7: Costa Rica | B7: JOVENMODA | C7: TIENDAS DE MODA | D7: GENERICO DE VENTAS PARA TIENDAS | E7: TIENDA BERSHKA DEL ESTE | F7: BERSHKA MULTIPLAZA DEL ESTE | G7: BUSTAMANTE SANCHEZ, JOSEPH JAVIER | H7: 2194803 | I7: SEGUNDO ENCARGADO | J7: 45005 | K7: DOMINGUEZ SALAZAR, BLAS ARTURO | L7: =VLOOKUP(H7,Sheet1!H:H,1,0) -> #N/A
A8: Costa Rica | B8: JOVENMODA | C8: TIENDAS DE MODA | D8: GENERICO DE VENTAS PARA TIENDAS | E8: TIENDA BERSHKA DEL ESTE | F8: BERSHKA MULTIPLAZA DEL ESTE | G8: CHINCHILLA LOPEZ, DONALD DANIER | H8: 2306303 | I8: DEPENDIENTE | J8: 45505 | K8: DOMINGUEZ SALAZAR, BLAS ARTURO | L8: =VLOOKUP(H8,Sheet1!H:H,1,0) -> #N/A
A9: Costa Rica | B9: JOVENMODA | C9: TIENDAS DE MODA | D9: GENERICO DE VENTAS PARA TIENDAS | E9: GERENCIA DE PAIS FRANQUICIAS COSTA RICA | F9: BERSHKA MULTIPLAZA DEL ESTE | G9: DOMINGUEZ SALAZAR, BLAS ARTURO | H9: 1718003 | I9: ENCARGADO GENERAL DE TIENDA | J9: 42814 | K9: AYALA AYALA, JOSET DEL CARMEN | L9: =VLOOKUP(H9,Sheet1!H:H,1,0) -> #N/A
A10: Costa Rica | B10: JOVENMODA | C10: TIENDAS DE MODA | D10: GENERICO DE VENTAS PARA TIENDAS | E10: TIENDA BERSHKA DEL ESTE | F10: BERSHKA MULTIPLAZA DEL ESTE | G10: LAGUNA VIDAURRE, DIEGO LEONEL | H10: 2474303 | I10: AUXILIAR DE ALMACEN | J10: 46038 | K10: DOMINGUEZ SALAZAR, BLAS ARTURO | L10: =VLOOKUP(H10,Sheet1!H:H,1,0) -> #N/A
A11: Costa Rica | B11: JOVENMODA | C11: TIENDAS DE MODA | D11: GENERICO DE VENTAS PARA TIENDAS | E11: TIENDA BERSHKA DEL ESTE | F11: BERSHKA MULTIPLAZA DEL ESTE | G11: MASIS JIMENEZ, LUIS FABIAN | H11: 2444003 | I11: AUXILIAR DE ALMACEN | J11: 46023 | K11: DOMINGUEZ SALAZAR, BLAS ARTURO | L11: =VLOOKUP(H11,Sheet1!H:H,1,0) -> #N/A
A12: Costa Rica | B12: JOVENMODA | C12: TIENDAS DE MODA | D12: GENERICO DE VENTAS PARA TIENDAS | E12: TIENDA BERSHKA DEL ESTE | F12: BERSHKA MULTIPLAZA DEL ESTE | G12: MOLINA CUBERO, JORGE ANDREY | H12: 2331203 | I12: DEPENDIENTE | J12: 45614 | K12: DOMINGUEZ SALAZAR, BLAS ARTURO | L12: =VLOOKUP(H12,Sheet1!H:H,1,0) -> #N/A
A13: Costa Rica | B13: JOVENMODA | C13: TIENDAS DE MODA | D13: GENERICO DE VENTAS PARA TIENDAS | E13: TIENDA BERSHKA DEL ESTE | F13: BERSHKA MULTIPLAZA DEL ESTE | G13: PALACIOS MATAMOROS, MANUEL FRANCISCO | H13: 2494403 | I13: DEPENDIENTE | J13: 46069 | K13: DOMINGUEZ SALAZAR, BLAS ARTURO | L13: =VLOOKUP(H13,Sheet1!H:H,1,0) -> #N/A
A14: Costa Rica | B14: JOVENMODA | C14: TIENDAS DE MODA | D14: GENERICO DE VENTAS PARA TIENDAS | E14: TIENDA BERSHKA DEL ESTE | F14: BERSHKA MULTIPLAZA DEL ESTE | G14: PINEDA MURILLO, NAYARA DESSYRETH | H14: 1506903 | I14: DEPENDIENTE | J14: 42023 | K14: DOMINGUEZ SALAZAR, BLAS ARTURO | L14: =VLOOKUP(H14,Sheet1!H:H,1,0) -> #N/A
... A275: Costa Rica | B275: EUROTIENDAS | C275: TIENDAS DE MODA | D275: GENERICO DE VENTAS PARA TIENDAS | E275: TIENDA ZARA ESCAZU | F275: ZARA MULTIPLAZA ESCAZU | G275: ZELEDON CALDERÓN, DAYANA VANESSA | H275: 2511103 | I275: DEPENDIENTE | J275: 46101 | K275: NAVARRETE MORALES, DIANA KAROLINA | L275: =VLOOKUP(H275,Sheet1!H:H,1,0) -> #N/A
A276: El Salvador | B276: ESPATIENDAS | C276: TIENDAS DE MODA | D276: GENERICO DE VENTAS PARA TIENDAS | E276: TIENDA OYSHO LA GRAN VIA | F276: OYSHO LA GRAN VIA | G276: BARRIOS CACERES, DANIELA ALEJANDRA | H276: 5007101 | I276: DEPENDIENTE | J276: 46090 | L276: =VLOOKUP(H276,Sheet1!H:H,1,0) -> #N/A
A277: El Salvador | B277: ESPATIENDAS | C277: TIENDAS DE MODA | D277: GENERICO DE VENTAS PARA TIENDAS | E277: TIENDA OYSHO LA GRAN VIA | F277: OYSHO LA GRAN VIA | G277: LOVO GUEVARA, JUAN CARLOS | H277: 4728801 | I277: DEPENDIENTE | J277: 45362 | L277: =VLOOKUP(H277,Sheet1!H:H,1,0) -> #N/A
A278: El Salvador | B278: ESPATIENDAS | C278: TIENDAS DE MODA | D278: GENERICO DE VENTAS PARA TIENDAS | E278: TIENDA OYSHO LA GRAN VIA | F278: OYSHO LA GRAN VIA | G278: SOLIS TAURA, SARA REBECA | H278: 4865701 | I278: DEPENDIENTE | J278: 45705 | L278: =VLOOKUP(H278,Sheet1!H:H,1,0) -> #N/A
A279: El Salvador | B279: IBEROMODA | C279: TIENDAS DE MODA | D279: GENERICO GERENCIA | E279: PRESIDENCIA EJECUTIVA FRANQUICIAS | F279: PULL & BEAR GALERIAS | G279: AVENDAÑO OSORIO, ANTONIO | H279: 3119101 | I279: GERENTE DE SISTEMAS | J279: 43328 | K279: PORTILLO SISNIEGA, PABLO EDGARDO | L279: =VLOOKUP(H279,Sheet1!H:H,1,0) -> #N/A
A280: El Salvador | B280: PROMODA | C280: TIENDAS DE MODA | D280: GENERICO GERENCIA | E280: PRESIDENCIA EJECUTIVA FRANQUICIAS | F280: PROMODA STRADIVARIUS GALERIAS | G280: AVILA MENDEZ, EDUARDO | H280: 4972401 | I280: ANALISTA DE NEGOCIO | J280: 45670 | K280: PORTILLO SISNIEGA, PABLO EDGARDO | L280: =VLOOKUP(H280,Sheet1!H:H,1,0) -> #N/A
A281: El Salvador | B281: EUROMODA | C281: TIENDAS DE MODA | D281: GENERICO DE VENTAS PARA TIENDAS | E281: TIENDA ZARA LA GRAN VIA | F281: EUROMODA ZARA LA GRA VIA | G281: AGUILAR GARCIA, EMELY SABRINA | H281: 5034201 | I281: DEPENDIENTE | J281: 45916 | K281: SANTOS DELGADO, PATRICIA ELIZABET | L281: =VLOOKUP(H281,Sheet1!H:H,1,0) -> #N/A
A282: El Salvador | B282: EUROMODA | C282: TIENDAS DE MODA | D282: GENERICO GERENCIA | E282: GERENCIA DE OBRAS Y MANTENIMIENTO FRANQUICIAS | F282: OFICINAS CORPORATIVAS | G282: AYALA CHACON, HECTOR ENRIQUE | H282: 2302901 | I282: SUPERVISOR DE MANTENIMIENTO | J282: 45215 | K282: CHAVEZ HERNANDEZ, ARMANDO RENE | L282: =VLOOKUP(H282,Sheet1!H:H,1,0) -> #N/A
A283: El Salvador | B283: EUROMODA | C283: TIENDAS VIRTUALES | D283: GENERICO DE VENTAS PARA TIENDAS | E283: TIENDA ZARA LA GRAN VIA | F283: EUROMODA ZARA LA GRA VIA | G283: COTAN VALDEZ, GERMAN EDENILSON | H283: 3040201 | I283: RESPONSABLE DE PACKING STORE | J283: 42109 | K283: SANTOS DELGADO, PATRICIA ELIZABET | L283: =VLOOKUP(H283,Sheet1!H:H,1,0) -> #N/A
A284: El Salvador | B284: PROMODA | C284: TIENDAS DE MODA | D284: GENERICO GERENCIA | E284: PRESIDENCIA EJECUTIVA FRANQUICIAS | F284: PROMODA STRADIVARIUS GALERIAS | G284: BUCARO SALVADOR, SANDRA CAROLINA | H284: 2032901 | I284: DIRECTOR COMERCIAL DE CADENA | J284: 40483 | K284: PORTILLO SISNIEGA, PABLO EDGARDO | L284: =VLOOKUP(H284,Sheet1!H:H,1,0) -> #N/A
A285: El Salvador | B285: EUROMODA | C285: TIENDAS DE MODA | D285: GENERICO DE VENTAS PARA TIENDAS | E285: TIENDA ZARA LA GRAN VIA | F285: EUROMODA ZARA LA GRA VIA | G285: AGUILLON CASTILLO, JACQUELINE ESTHER | H285: 5200101 | I285: DEPENDIENTE | J285: 46054 | K285: SANTOS DELGADO, PATRICIA ELIZABET | L285: =VLOOKUP(H285,Sheet1!H:H,1,0) -> #N/A
A286: El Salvador | B286: EUROMODA | C286: TIENDAS DE MODA | D286: GENERICO DE VENTAS PARA TIENDAS | E286: TIENDA ZARA LA GRAN VIA | F286: EUROMODA ZARA LA GRA VIA | G286: ALVARADO MELARA, LISBETH GABRIELA | H286: 5164601 | I286: AUXILIAR DE ALMACEN | J286: 45985 | K286: SANTOS DELGADO, PATRICIA ELIZABET | L286: =VLOOKUP(H286,Sheet1!H:H,1,0) -> #N/A
A287: El Salvador | B287: EUROMODA | C287: TIENDAS DE MODA | D287: GENERICO DE VENTAS PARA TIENDAS | E287: TIENDA ZARA LA GRAN VIA | F287: EUROMODA ZARA LA GRA VIA | G287: AREVALO BLANCO, ROBERTO CHRISTOPHER | H287: 4955701 | I287: AUXILIAR DE ALMACEN | J287: 45607 | K287: SANTOS DELGADO, PATRICIA ELIZABET | L287: =VLOOKUP(H287,Sheet1!H:H,1,0) -> #N/A
A288: El Salvador | B288: EUROMODA | C288: TIENDAS DE MODA | D288: GENERICO DE VENTAS PARA TIENDAS | E288: TIENDA ZARA LA GRAN VIA | F288: EUROMODA ZARA LA GRA VIA | G288: ARGUETA GONZALEZ, ILEANA | H288: 4784501 | I288: DEPENDIENTE | J288: 45516 | K288: SANTOS DELGADO, PATRICIA ELIZABET | L288: =VLOOKUP(H288,Sheet1!H:H,1,0) -> #N/A
A289: El Salvador | B289: EUROMODA | C289: TIENDAS DE MODA | D289: GENERICO DE VENTAS PARA TIENDAS | E289: TIENDA ZARA LA GRAN VIA | F289: EUROMODA ZARA LA GRA VIA | G289: BARRERA RAMIRIOS, DANIELA TAMARA | H289: 4307701 | I289: JEFE DE OPERACIONES | J289: 44697 | K289: SANTOS DELGADO, PATRICIA ELIZABET | L289: =VLOOKUP(H289,Sheet1!H:H,1,0) -> #N/A
A290: El Salvador | B290: EUROMODA | C290: TIENDAS DE MODA | D290: GENERICO DE VENTAS PARA TIENDAS | E290: TIENDA ZARA LA GRAN VIA | F290: EUROMODA ZARA LA GRA VIA | G290: BARRIENTOS VALENZUELA, DANIELA ALEXANDRA | H290: 4710001 | I290: DEPENDIENTE | J290: 46062 | K290: SANTOS DELGADO, PATRICIA ELIZABET | L290: =VLOOKUP(H290,Sheet1!H:H,1,0) -> #N/A
... A376: El Salvador | B376: IBEROMODA | C376: TIENDAS DE MODA | D376: GENERICO GERENCIA | E376: DIRECCION DE RECURSOS HUMANOS FRANQUICIAS | F376: PULL & BEAR GALERIAS | G376: MENJIVAR QUINTANILLA, JOSE HERIBERTO | H376: 3603201 | I376: JEFE CORPORATIVO DE PREVENCION Y SALUD OCUPACIONAL | J376: 45901 | K376: GUERRERO MEDRANO, ROXANA LIZETH | L376: =VLOOKUP(H376,Sheet1!H:H,1,0) -> #N/A
A377: El Salvador | B377: JOVENMODA | C377: TIENDAS DE MODA | D377: GENERICO DE VENTAS PARA TIENDAS | E377: TIENDA BERSHKA LA GRAN VIA | F377: BERSHKA LA GRA VIA | G377: FUENTES RIVAS, JOSE ANTONIO | H377: 4789701 | I377: DEPENDIENTE | J377: 45593 | L377: =VLOOKUP(H377,Sheet1!H:H,1,0) -> #N/A
A378: El Salvador | B378: IBEROMODA | C378: TIENDAS DE MODA | D378: GENERICO GERENCIA | E378: GERENCIA DE INVENTARIOS FRANQUICIAS | F378: PULL & BEAR GALERIAS | G378: MOLINA DE ALAS, ALMA LISSETH | H378: 3820001 | I378: AUXILIAR DE CONTROL DE INVENTARIOS | J378: 43647 | K378: RIVERA RIVAS, SILVIA MARIA | L378: =VLOOKUP(H378,Sheet1!H:H,1,0) -> #N/A
A379: El Salvador | B379: JOVENMODA | C379: TIENDAS DE MODA | D379: GENERICO DE VENTAS PARA TIENDAS | E379: TIENDA BERSHKA LA GRAN VIA | F379: BERSHKA LA GRA VIA | G379: DERAS SALINAS, KEYRI ARIANA | H379: 4933801 | I379: DEPENDIENTE | J379: 45593 | L379: =VLOOKUP(H379,Sheet1!H:H,1,0) -> #N/A
A380: El Salvador | B380: JOVENMODA | C380: TIENDAS DE MODA | D380: GENERICO DE VENTAS PARA TIENDAS | E380: TIENDA BERSHKA GALERIAS | F380: BERSHKA GALERIAS | G380: OSORIO SOLORZANO, JUAN ERNESTO | H380: 4991001 | I380: DEPENDIENTE | J380: 45771 | K380: MARROQUIN PINEDA, ANDREA NICOLE | L380: =VLOOKUP(H380,Sheet1!H:H,1,0) -> #N/A
A381: El Salvador | B381: JOVENMODA | C381: TIENDAS DE MODA | D381: GENERICO DE VENTAS PARA TIENDAS | E381: TIENDA BERSHKA LA GRAN VIA | F381: BERSHKA LA GRA VIA | G381: MENJIVAR RUBIO, DIEGO ALEJANDRO | H381: 5007001 | I381: DEPENDIENTE | J381: 45831 | L381: =VLOOKUP(H381,Sheet1!H:H,1,0) -> #N/A
A382: El Salvador | B382: JOVENMODA | C382: TIENDAS DE MODA | D382: GENERICO DE VENTAS PARA TIENDAS | E382: TIENDA BERSHKA LA GRAN VIA | F382: BERSHKA LA GRA VIA | G382: RUBALLO CARDENAS, DAMARIS GISSELLE | H382: 4912801 | I382: DEPENDIENTE | J382: 45593 | L382: =VLOOKUP(H382,Sheet1!H:H,1,0) -> #N/A
A383: El Salvador | B383: JOVENMODA | C383: TIENDAS DE MODA | D383: GENERICO DE VENTAS PARA TIENDAS | E383: TIENDA BERSHKA LA GRAN VIA | F383: BERSHKA LA GRA VIA | G383: BARAHONA CABRERA, CLARISSA SARAI | H383: 4913001 | I383: DEPENDIENTE | J383: 45593 | L383: =VLOOKUP(H383,Sheet1!H:H,1,0) -> #N/A
A384: El Salvador | B384: JOVENMODA | C384: TIENDAS DE MODA | D384: GENERICO DE VENTAS PARA TIENDAS | E384: TIENDA BERSHKA GALERIAS | F384: BERSHKA GALERIAS | G384: VILLANUEVA BELTRAN, BRANDON DAGOBERTO | H384: 5117301 | I384: AUXILIAR DE ALMACEN | J384: 45957 | K384: MARROQUIN PINEDA, ANDREA NICOLE | L384: =VLOOKUP(H384,Sheet1!H:H,1,0) -> #N/A
A385: El Salvador | B385: JOVENMODA | C385: TIENDAS DE MODA | D385: GENERICO DE VENTAS PARA TIENDAS | E385: TIENDA BERSHKA LA GRAN VIA | F385: BERSHKA LA GRA VIA | G385: ALVARADO MELARA, ALEXYS GABRIEL | H385: 4913201 | I385: DEPENDIENTE | J385: 45593 | L385: =VLOOKUP(H385,Sheet1!H:H,1,0) -> #N/A
A386: El Salvador | B386: JOVENMODA | C386: TIENDAS DE MODA | D386: GENERICO DE VENTAS PARA TIENDAS | E386: TIENDA BERSHKA GALERIAS | F386: BERSHKA GALERIAS | G386: CRUZ LOPEZ, HAZEL NICOLE | H386: 4953301 | I386: DEPENDIENTE | J386: 45614 | K386: MARROQUIN PINEDA, ANDREA NICOLE | L386: =VLOOKUP(H386,Sheet1!H:H,1,0) -> #N/A
A387: El Salvador | B387: JOVENMODA | C387: TIENDAS DE MODA | D387: GENERICO GERENCIA | E387: DIRECCION DE RECURSOS HUMANOS FRANQUICIAS | F387: OFICINAS CORPORATIVAS | G387: MORAN CUELLAR, OSIRIS GABRIEL | H387: 3607801 | I387: COORDINADOR DE DESARROLLO ORGANIZACIONAL | J387: 46023 | K387: GUERRERO MEDRANO, ROXANA LIZETH | L387: =VLOOKUP(H387,Sheet1!H:H,1,0) -> 3607801
A388: El Salvador | B388: JOVENMODA | C388: TIENDAS DE MODA | D388: GENERICO DE VENTAS PARA TIENDAS | E388: TIENDA BERSHKA LA GRAN VIA | F388: BERSHKA LA GRA VIA | G388: CANTORAL ECHEVERRIA, STEVEN ANTONIO | H388: 4866201 | I388: DEPENDIENTE | J388: 45587 | L388: =VLOOKUP(H388,Sheet1!H:H,1,0) -> #N/A
A389: El Salvador | B389: JOVENMODA | C389: TIENDAS DE MODA | D389: GENERICO DE VENTAS PARA TIENDAS | E389: TIENDA BERSHKA LA GRAN VIA | F389: BERSHKA LA GRA VIA | G389: REYES GOMEZ, ANDY ALEXANDERSSON | H389: 4866301 | I389: DEPENDIENTE | J389: 45586 | L389: =VLOOKUP(H389,Sheet1!H:H,1,0) -> #N/A
A390: El Salvador | B390: JOVENMODA | C390: TIENDAS DE MODA | D390: GENERICO DE VENTAS PARA TIENDAS | E390: TIENDA BERSHKA GALERIAS | F390: BERSHKA GALERIAS | G390: PALACIOS ALAS, NATHALY GISSELA | H390: 4728701 | I390: TERCER ENCARGADO | J390: 45362 | K390: MARROQUIN PINEDA, ANDREA NICOLE | L390: =VLOOKUP(H390,Sheet1!H:H,1,0) -> #N/A
A391: El Salvador | B391: JOVENMODA | C391: TIENDAS DE MODA | D391: GENERICO DE VENTAS PARA TIENDAS | E391: TIENDA BERSHKA LA GRAN VIA | F391: BERSHKA LA GRA VIA | G391: HERRERA GUERRERO, ROBERTO ENRIQUE | H391: 4867101 | I391: DEPENDIENTE | J391: 45588 | L391: =VLOOKUP(H391,Sheet1!H:H,1,0) -> #N/A
A392: El Salvador | B392: JOVENMODA | C392: TIENDAS DE MODA | D392: GENERICO DE VENTAS PARA TIENDAS | E392: TIENDA BERSHKA LA GRAN VIA | F392: BERSHKA LA GRA VIA | G392: RIVERA LOZANO, DAVID SAMUEL | H392: 5032301 | I392: AUXILIAR DE ALMACEN | J392: 45908 | L392: =VLOOKUP(H392,Sheet1!H:H,1,0) -> #N/A
A393: El Salvador | B393: JOVENMODA | C393: TIENDAS DE MODA | D393: GENERICO DE VENTAS PARA TIENDAS | E393: GERENCIA DE RECURSOS HUMANOS FRANQUICIAS | F393: BERSHKA GALERIAS | G393: MARROQUIN PINEDA, ANDREA NICOLE | H393: 3431301 | I393: ENCARGADO GENERAL DE TIENDA | J393: 42902 | K393: LINARES RAMOS, DALIDE MARCELLA | L393: =VLOOKUP(H393,Sheet1!H:H,1,0) -> #N/A
A394: El Salvador | B394: EUROMODA | C394: TIENDAS DE MODA | D394: GENERICO GERENCIA | E394: PRESIDENCIA EJECUTIVA FRANQUICIAS | F394: EUROMODA ZARA GALERIAS | G394: MUNDO ORELLANA, CRISTINA GUADALUPE | H394: 4544501 | I394: ASISTENTE DE DIRECCION | J394: 45154 | K394: PORTILLO SISNIEGA, PABLO EDGARDO | L394: =VLOOKUP(H394,Sheet1!H:H,1,0) -> #N/A
A395: El Salvador | B395: JOVENMODA | C395: TIENDAS DE MODA | D395: GENERICO GERENCIA | E395: GERENCIA DE IMPORTACIONES FRANQUICIAS | F395: OFICINAS CORPORATIVAS | G395: NAJERA ESCOBAR, JENNIFER MIRELLA | H395: 4286901 | I395: AUXILIAR DE IMPORTACIONES Y RETACEOS | J395: 44652 | K395: RIVAS LOPEZ, LIZETH EUNICE | L395: =VLOOKUP(H395,Sheet1!H:H,1,0) -> #N/A
A396: El Salvador | B396: IBEROMODA | C396: TIENDAS DE MODA | D396: GENERICO GERENCIA | E396: PRESIDENCIA EJECUTIVA FRANQUICIAS | F396: PULL & BEAR GALERIAS | G396: NOCHEZ DE BERMUDEZ, LUCCIANA | H396: 4793401 | I396: DIRECTOR COMERCIAL DE CADENA | J396: 45530 | K396: PORTILLO SISNIEGA, PABLO EDGARDO | L396: =VLOOKUP(H396,Sheet1!H:H,1,0) -> #N/A
A397: El Salvador | B397: IBEROMODA | C397: TIENDAS DE MODA | D397: GENERICO GERENCIA | E397: CONTABILIDAD CORPORATIVA FRANQUICIAS | F397: OFICINAS CORPORATIVAS | G397: OLMOS HERNANDEZ, DOUGLAS ULISES | H397: 4827701 | I397: ANALISTA CONTABLE | J397: 45566 | K397: VIVAS APARICIO, SILVIA ELENA | L397: =VLOOKUP(H397,Sheet1!H:H,1,0) -> #N/A
A398: El Salvador | B398: JOVENMODA | C398: TIENDAS DE MODA | D398: GENERICO DE VENTAS PARA TIENDAS | E398: TIENDA BERSHKA LA GRAN VIA | F398: BERSHKA LA GRA VIA | G398: FUENTES CAÑADA, RENE OSVALDO | H398: 3633201 | I398: ENCARGADO DE CHICO | J398: 43325 | L398: =VLOOKUP(H398,Sheet1!H:H,1,0) -> #N/A
A399: El Salvador | B399: JOVENMODA | C399: TIENDAS DE MODA | D399: GENERICO DE VENTAS PARA TIENDAS | E399: TIENDA BERSHKA GALERIAS | F399: BERSHKA GALERIAS | G399: COREAS CUELLAR, ALLAN EDUARDO | H399: 4285201 | I399: SEGUNDO ENCARGADO | J399: 45516 | K399: MARROQUIN PINEDA, ANDREA NICOLE | L399: =VLOOKUP(H399,Sheet1!H:H,1,0) -> #N/A
A400: El Salvador | B400: JOVENMODA | C400: TIENDAS DE MODA | D400: GENERICO DE VENTAS PARA TIENDAS | E400: TIENDA BERSHKA LA GRAN VIA | F400: BERSHKA LA GRA VIA | G400: LOPEZ MARTINEZ, HERIBERTO ALEXANDER | H400: 4321201 | I400: AUXILIAR DE ALMACEN | J400: 44774 | L400: =VLOOKUP(H400,Sheet1!H:H,1,0) -> #N/A
A401: El Salvador | B401: JOVENMODA | C401: TIENDAS DE MODA | D401: GENERICO GERENCIA | E401: GERENCIA DE RECURSOS HUMANOS FRANQUICIAS | F401: BERSHKA GALERIAS | G401: ORTIZ TRIGUEROS, KRISIA STEPHANIA | H401: 3633101 | I401: TECNICO DE RECLUTAMIENTO | J401: 43313 | K401: LINARES RAMOS, DALIDE MARCELLA | L401: =VLOOKUP(H401,Sheet1!H:H,1,0) -> #N/A
A402: El Salvador | B402: JOVENMODA | C402: TIENDAS DE MODA | D402: GENERICO DE VENTAS PARA TIENDAS | E402: TIENDA BERSHKA LA GRAN VIA | F402: BERSHKA LA GRA VIA | G402: GIRON SOLORZANO, ANDREA YASHIRA | H402: 4327401 | I402: TERCER ENCARGADO | J402: 44758 | L402: =VLOOKUP(H402,Sheet1!H:H,1,0) -> #N/A
A403: El Salvador | B403: JOVENMODA | C403: TIENDAS DE MODA | D403: GENERICO DE VENTAS PARA TIENDAS | E403: TIENDA BERSHKA LA GRAN VIA | F403: BERSHKA LA GRA VIA | G403: MARTINEZ MOLINA, DIEGO ROLANDO | H403: 5006101 | I403: DEPENDIENTE | J403: 45831 | L403: =VLOOKUP(H403,Sheet1!H:H,1,0) -> #N/A
A404: El Salvador | B404: JOVENMODA | C404: TIENDAS DE MODA | D404: GENERICO DE VENTAS PARA TIENDAS | E404: TIENDA BERSHKA GALERIAS | F404: BERSHKA GALERIAS | G404: JUAREZ, BEKYS JASMIN | H404: 2573001 | I404: DEPENDIENTE | J404: 41099 | K404: MARROQUIN PINEDA, ANDREA NICOLE | L404: =VLOOKUP(H404,Sheet1!H:H,1,0) -> #N/A
A405: El Salvador | B405: JOVENMODA | C405: TIENDAS DE MODA | D405: GENERICO DE VENTAS PARA TIENDAS | E405: TIENDA BERSHKA LA GRAN VIA | F405: BERSHKA LA GRA VIA | G405: RODRIGUEZ MENA, CHRISTOPHER ANTONIO | H405: 4640301 | I405: DEPENDIENTE | J405: 45593 | L405: =VLOOKUP(H405,Sheet1!H:H,1,0) -> #N/A
A406: El Salvador | B406: NORDICORP EL SALVADOR | C406: TIENDAS DE BIENES DIVERSOS AL DETALLE | D406: GENERICO GERENCIA | E406: PRESIDENCIA EJECUTIVA FRANQUICIAS | F406: NORDICORP SV | G406: MARTINEZ PORTILLO, MARCELA EUGENIA | H406: 1863401 | I406: DIRECTOR DE MARCA | J406: 46082 | K406: PORTILLO SISNIEGA, PABLO EDGARDO | L406: =VLOOKUP(H406,Sheet1!H:H,1,0) -> #N/A
A407: El Salvador | B407: NORDICORP EL SALVADOR | C407: TIENDAS DE BIENES DIVERSOS AL DETALLE | D407: GENERICO GERENCIA | E407: PRESIDENCIA EJECUTIVA FRANQUICIAS | F407: NORDICORP SV | G407: PAREDES PELEGERO, DANIELA MARIA | H407: 2411201 | I407: GERENTE DE OPERACION RETAIL | J407: 42782 | K407: PORTILLO SISNIEGA, PABLO EDGARDO | L407: =VLOOKUP(H407,Sheet1!H:H,1,0) -> #N/A
A408: El Salvador | B408: NORDICORP EL SALVADOR | C408: TIENDAS DE BIENES DIVERSOS AL DETALLE | D408: GENERICO GERENCIA | E408: GERENCIA DE OBRAS Y MANTENIMIENTO FRANQUICIAS | F408: NORDICORP SV | G408: RIVERA CAMPOS, SIRHAN GERARDO | H408: 5202201 | I408: GERENTE DE OBRAS NUEVAS MARCAS | J408: 46069 | K408: CHAVEZ HERNANDEZ, ARMANDO RENE | L408: =VLOOKUP(H408,Sheet1!H:H,1,0) -> #N/A
A409: El Salvador | B409: NORDICORP EL SALVADOR | C409: TIENDAS DE BIENES DIVERSOS AL DETALLE | D409: GENERICO GERENCIA | E409: PRESIDENCIA EJECUTIVA FRANQUICIAS | F409: NORDICORP SV | G409: TORRES MARTINEZ, ROCIO DEL CARMEN | H409: 4285101 | I409: GERENTE DE MERCANCIAS | J409: 46082 | K409: PORTILLO SISNIEGA, PABLO EDGARDO | L409: =VLOOKUP(H409,Sheet1!H:H,1,0) -> #N/A
A410: El Salvador | B410: PROMODA | C410: TIENDAS DE MODA | D410: GENERICO DE VENTAS PARA TIENDAS | E410: TIENDA STRADIVARIUS GALERIAS | F410: PROMODA STRADIVARIUS GALERIAS | G410: ALFARO REYES, CHRISTIAN IVAN | H410: 4956001 | I410: AUXILIAR DE ALMACEN | J410: 45705 | K410: CABALLERO AYALA, MARIO ERNESTO | L410: =VLOOKUP(H410,Sheet1!H:H,1,0) -> #N/A
A411: El Salvador | B411: PROMODA | C411: TIENDAS DE MODA | D411: GENERICO GERENCIA | E411: CONTABILIDAD CORPORATIVA FRANQUICIAS | F411: PROMODA STRADIVARIUS GALERIAS | G411: PINEDA QUIUSQUI, IVAN ALEXIS | H411: 4588101 | I411: ENCARGADO ARCHIVO | J411: 45530 | K411: VIVAS APARICIO, SILVIA ELENA | L411: =VLOOKUP(H411,Sheet1!H:H,1,0) -> #N/A
A412: El Salvador | B412: PROMODA | C412: TIENDAS DE MODA | D412: GENERICO DE VENTAS PARA TIENDAS | E412: TIENDA STRADIVARIUS GALERIAS | F412: PROMODA STRADIVARIUS GALERIAS | G412: BONILLA DURAN, KIMBERLY NICOLE | H412: 5008401 | I412: DEPENDIENTE | J412: 45894 | K412: CABALLERO AYALA, MARIO ERNESTO | L412: =VLOOKUP(H412,Sheet1!H:H,1,0) -> #N/A
A413: El Salvador | B413: PROMODA | C413: TIENDAS DE MODA | D413: GENERICO DE VENTAS PARA TIENDAS | E413: TIENDA STRADIVARIUS LA GRAN VIA | F413: STRADIVARIUS LA GRAN VIA | G413: ACOSTA ESCOBAR, JASON LEONEL | H413: 5028801 | I413: DEPENDIENTE | J413: 45894 | K413: FIGUEROA CALLES, MARIA JOHANA | L413: =VLOOKUP(H413,Sheet1!H:H,1,0) -> #N/A
A414: El Salvador | B414: PROMODA | C414: TIENDAS DE MODA | D414: GENERICO DE VENTAS PARA TIENDAS | E414: TIENDA STRADIVARIUS LA GRAN VIA | F414: STRADIVARIUS LA GRAN VIA | G414: MORALES JORDAN, DAVID MOISES | H414: 5028901 | I414: DEPENDIENTE | J414: 45894 | K414: FIGUEROA CALLES, MARIA JOHANA | L414: =VLOOKUP(H414,Sheet1!H:H,1,0) -> #N/A
A415: El Salvador | B415: PROMODA | C415: TIENDAS DE MODA | D415: GENERICO DE VENTAS PARA TIENDAS | E415: TIENDA STRADIVARIUS LA GRAN VIA | F415: STRADIVARIUS LA GRAN VIA | G415: ARAUJO HERNANDEZ, ZOE NICOLE | H415: 5028401 | I415: DEPENDIENTE | J415: 45894 | K415: FIGUEROA CALLES, MARIA JOHANA | L415: =VLOOKUP(H415,Sheet1!H:H,1,0) -> #N/A
A416: El Salvador | B416: PROMODA | C416: TIENDAS DE MODA | D416: GENERICO DE VENTAS PARA TIENDAS | E416: TIENDA STRADIVARIUS LA GRAN VIA | F416: STRADIVARIUS LA GRAN VIA | G416: SOLIS SOLIS, HALLE ALEXANDRA | H416: 5029001 | I416: DEPENDIENTE | J416: 45894 | K416: FIGUEROA CALLES, MARIA JOHANA | L416: =VLOOKUP(H416,Sheet1!H:H,1,0) -> #N/A
A417: El Salvador | B417: PROMODA | C417: TIENDAS DE MODA | D417: GENERICO DE VENTAS PARA TIENDAS | E417: TIENDA STRADIVARIUS LA GRAN VIA | F417: STRADIVARIUS LA GRAN VIA | G417: BENITEZ RODRIGUEZ, LESLIE ANDREA | H417: 4934201 | I417: DEPENDIENTE | J417: 45600 | K417: FIGUEROA CALLES, MARIA JOHANA | L417: =VLOOKUP(H417,Sheet1!H:H,1,0) -> #N/A
... A424: El Salvador | B424: PROMODA | C424: TIENDAS DE MODA | D424: GENERICO DE VENTAS PARA TIENDAS | E424: TIENDA STRADIVARIUS LA GRAN VIA | F424: STRADIVARIUS LA GRAN VIA | G424: ARGUETA MENDOZA, NATALIA VIRGINIA | H424: 4611901 | I424: DEPENDIENTE | J424: 45362 | K424: FIGUEROA CALLES, MARIA JOHANA | L424: =VLOOKUP(H424,Sheet1!H:H,1,0) -> #N/A
A425: El Salvador | B425: EUROMODA | C425: TIENDAS DE MODA | D425: GENERICO GERENCIA | E425: PRESIDENCIA ALSICORP | F425: OFICINAS ADMINISTRATIVAS | G425: PORTILLO SISNIEGA, PABLO EDGARDO | H425: 2165101 | I425: CEO FRANQUICIAS | J425: 40120 | L425: =VLOOKUP(H425,Sheet1!H:H,1,0) -> #N/A
A426: El Salvador | B426: PROMODA | C426: TIENDAS DE MODA | D426: GENERICO DE VENTAS PARA TIENDAS | E426: TIENDA STRADIVARIUS LA GRAN VIA | F426: STRADIVARIUS LA GRAN VIA | G426: CABRERA ALVARADO, CRISTIAN ORLANDO | H426: 4765001 | I426: DEPENDIENTE | J426: 45558 | K426: FIGUEROA CALLES, MARIA JOHANA | L426: =VLOOKUP(H426,Sheet1!H:H,1,0) -> #N/A
A427: El Salvador | B427: PROMODA | C427: TIENDAS DE MODA | D427: GENERICO GERENCIA | E427: PRESIDENCIA EJECUTIVA FRANQUICIAS | F427: PROMODA STRADIVARIUS GALERIAS | G427: RIVAS LOPEZ, LIZETH EUNICE | H427: 2748201 | I427: GERENTE DE IMPORTACIONES FRANQUICIAS | J427: 43678 | K427: PORTILLO SISNIEGA, PABLO EDGARDO | L427: =VLOOKUP(H427,Sheet1!H:H,1,0) -> #N/A
A428: El Salvador | B428: IBEROMODA | C428: TIENDAS DE MODA | D428: GENERICO GERENCIA | E428: PRESIDENCIA EJECUTIVA FRANQUICIAS | F428: PULL & BEAR GALERIAS | G428: RIVERA RIVAS, SILVIA MARIA | H428: 2710101 | I428: GERENTE DE CONTROL DE INVENTARIOS FRANQUICIAS | J428: 43252 | K428: PORTILLO SISNIEGA, PABLO EDGARDO | L428: =VLOOKUP(H428,Sheet1!H:H,1,0) -> #N/A
A429: El Salvador | B429: PROMODA | C429: TIENDAS DE MODA | D429: GENERICO DE VENTAS PARA TIENDAS | E429: TIENDA STRADIVARIUS GALERIAS | F429: PROMODA STRADIVARIUS GALERIAS | G429: HERNANDEZ RODRIGUEZ, NATHALY ADRIANA | H429: 4967201 | I429: DEPENDIENTE | J429: 45831 | K429: CABALLERO AYALA, MARIO ERNESTO | L429: =VLOOKUP(H429,Sheet1!H:H,1,0) -> #N/A
A430: El Salvador | B430: PROMODA | C430: TIENDAS DE MODA | D430: GENERICO DE VENTAS PARA TIENDAS | E430: GERENCIA DE RECURSOS HUMANOS FRANQUICIAS | F430: PROMODA STRADIVARIUS GALERIAS | G430: HERNANDEZ SALMERON, GLADYS ALEXIA | H430: 3163701 | I430: ENCARGADO GENERAL DE TIENDA | J430: 42387 | K430: LINARES RAMOS, DALIDE MARCELLA | L430: =VLOOKUP(H430,Sheet1!H:H,1,0) -> #N/A
A431: El Salvador | B431: PROMODA | C431: TIENDAS DE MODA | D431: GENERICO DE VENTAS PARA TIENDAS | E431: TIENDA STRADIVARIUS LA GRAN VIA | F431: STRADIVARIUS LA GRAN VIA | G431: GUARDADO CORNEJO, EDWARD MARDOQUEO | H431: 4919801 | I431: DEPENDIENTE | J431: 45593 | K431: FIGUEROA CALLES, MARIA JOHANA | L431: =VLOOKUP(H431,Sheet1!H:H,1,0) -> #N/A
A432: El Salvador | B432: IBEROMODA | C432: TIENDAS DE MODA | D432: GENERICO GERENCIA | E432: GERENCIA DE INVENTARIOS FRANQUICIAS | F432: PULL & BEAR GALERIAS | G432: RODRIGUEZ MEZA, FRANCISCO JOSE | H432: 3430701 | I432: RESPONSABLE AMT PAIS | J432: 42902 | K432: RIVERA RIVAS, SILVIA MARIA | L432: =VLOOKUP(H432,Sheet1!H:H,1,0) -> #N/A
A433: El Salvador | B433: PROMODA | C433: TIENDAS DE MODA | D433: GENERICO DE VENTAS PARA TIENDAS | E433: TIENDA STRADIVARIUS GALERIAS | F433: PROMODA STRADIVARIUS GALERIAS | G433: PANIAGUA ESCOBAR, NICOLE ALEXANDRA | H433: 4528101 | I433: DEPENDIENTE | J433: 45096 | K433: CABALLERO AYALA, MARIO ERNESTO | L433: =VLOOKUP(H433,Sheet1!H:H,1,0) -> #N/A
A434: El Salvador | B434: IBEROMODA | C434: TIENDAS DE MODA | D434: GENERICO GERENCIA | E434: GERENCIA DE IMPORTACIONES FRANQUICIAS | F434: PULL & BEAR GALERIAS | G434: RODRIGUEZ MONGE, GABRIELA ALEJANDRA | H434: 4806001 | I434: AUXILIAR DE IMPORTACIONES | J434: 45552 | K434: RIVAS LOPEZ, LIZETH EUNICE | L434: =VLOOKUP(H434,Sheet1!H:H,1,0) -> #N/A
A435: El Salvador | B435: PROMODA | C435: TIENDAS DE MODA | D435: GENERICO DE VENTAS PARA TIENDAS | E435: TIENDA STRADIVARIUS GALERIAS | F435: PROMODA STRADIVARIUS GALERIAS | G435: RIVERA HERNANDEZ, CLAUDIA MARIA | H435: 4914101 | I435: DEPENDIENTE | J435: 45593 | K435: CABALLERO AYALA, MARIO ERNESTO | L435: =VLOOKUP(H435,Sheet1!H:H,1,0) -> #N/A
A436: El Salvador | B436: PROMODA | C436: TIENDAS DE MODA | D436: GENERICO DE VENTAS PARA TIENDAS | E436: TIENDA STRADIVARIUS GALERIAS | F436: PROMODA STRADIVARIUS GALERIAS | G436: VALLECILLOS ALFARO, MARIANA SOPHIA | H436: 4900101 | I436: DEPENDIENTE | J436: 45719 | K436: CABALLERO AYALA, MARIO ERNESTO | L436: =VLOOKUP(H436,Sheet1!H:H,1,0) -> #N/A
A437: El Salvador | B437: PROMODA | C437: TIENDAS DE MODA | D437: GENERICO DE VENTAS PARA TIENDAS | E437: GERENCIA DE RECURSOS HUMANOS FRANQUICIAS | F437: STRADIVARIUS LA GRAN VIA | G437: FIGUEROA CALLES, MARIA JOHANA | H437: 3501901 | I437: ENCARGADO GENERAL DE TIENDA | J437: 43031 | K437: LINARES RAMOS, DALIDE MARCELLA | L437: =VLOOKUP(H437,Sheet1!H:H,1,0) -> #N/A
... A1138: Nicaragua | B1138: EUROTIENDAS | C1138: TIENDAS DE MODA | D1138: GENERICO DE VENTAS PARA TIENDAS | E1138: TIENDA ZARA SANTO DOMINGO | F1138: ZARA SANTO DOMINGO | G1138: ZUNIGA DAVILA, MASSIEL STEFANY | H1138: 1450205 | I1138: ENCARGADO(A) DE SECCION NIÑOS | J1138: 44136 | K1138: FLORES GUILLEN, JENIFFER KASSANDRA | L1138: =VLOOKUP(H1138,Sheet1!H:H,1,0) -> #N/A
